{
  "execution_time": {
    "start": "2025-09-06T00:50:00Z",
    "end": "2025-09-06T01:30:00Z",
    "duration_minutes": 40
  },
  "phases": [
    {
      "id": "PHASE-6",
      "title": "Agent Execution & Workflow Integration",
      "stories": {
        "STORY-6.1": {
          "status": "GREEN",
          "tasks_completed": 2,
          "tests_passed": ["TC-20.1", "TC-22.1"],
          "commit": "809c64a"
        },
        "STORY-6.2": {
          "status": "GREEN",
          "tasks_completed": 2,
          "tests_passed": ["TC-21.1"],
          "commit": "7f5f79a"
        }
      },
      "finalVerdict": "GREEN",
      "retries": {
        "STORY-6.1": 0,
        "STORY-6.2": 0
      },
      "phase_gate": {
        "regression_test": "PASS",
        "final_commit": "65c6631"
      }
    }
  ],
  "overall": "GREEN",
  "statistics": {
    "total_stories": 2,
    "stories_passed": 2,
    "stories_failed": 0,
    "total_tests": 3,
    "tests_passed": 3,
    "tests_failed": 0,
    "total_commits": 3,
    "total_retries": 0
  },
  "requirements_fulfilled": [
    "ARCH-008",
    "ARCH-010",
    "PROD-014",
    "PROD-016",
    "USER-008",
    "USER-010"
  ],
  "evidence_paths": {
    "phase_summary": "./evidence/PHASE-6/phase-summary.md",
    "story_6_1": "./evidence/PHASE-6/story-6.1-evidence.md",
    "story_6_2": "./evidence/PHASE-6/story-6.2-evidence.md",
    "traceability": ".pm/system/common/traceability.md"
  },
  "policies_applied": {
    "docker_rebuild_before_tests": true,
    "lint_strict": true,
    "vuln_fail_levels": ["CRITICAL", "HIGH"],
    "qa_can_repair_traceability": true,
    "qa_max_retries_per_story": 1,
    "qa_max_retries_phase_gate": 1
  },
  "notes": "Phase 6 completed successfully with no retries required. All stories passed on first attempt with full test coverage and documentation."
}